Metadata-Version: 2.4
Name: neuromancer
Version: 1.5.6
Summary: Neural Modules with Adaptive Nonlinear Constraints and Efficient Regularization
Author-email: Jan Drgona <jdrgona1@jh.edu>, Aaron Tuor <aaron.tuor@pnnl.gov>, James Koch <james.koch@pnnl.gov>, Madelyn Shapiro <madelyn.shapiro@pnnl.gov>, Rahul Birmiwal <rahul.birmiwal@pnnl.gov>, Draguna Vrabie <draguna.vrabie@pnnl.gov>, Bruno Jacob <bruno.jacob@pnnl.gov>, Reilly Raab <reilly.raab@pnnl.gov>
License: BSD-2-Clause
Project-URL: homepage, https://github.com/pnnl/neuromancer/
Project-URL: documentation, https://github.com/pnnl/neuromancer/
Project-URL: repository, https://github.com/pnnl/neuromancer/
Keywords: Deep Learning,Pytorch,Scientific Machine Learning,Dynamical Systems,Data-driven control
Classifier: Programming Language :: Python :: 3.9
Classifier: Programming Language :: Python :: 3.10
Classifier: Programming Language :: Python :: 3.11
Classifier: Programming Language :: Python :: 3.12
Classifier: Operating System :: OS Independent
Classifier: Topic :: Scientific/Engineering :: Artificial Intelligence
Classifier: Topic :: Scientific/Engineering :: Physics
Classifier: License :: OSI Approved :: BSD License
Requires-Python: >=3.9
License-File: LICENSE.md
Requires-Dist: dill
Requires-Dist: graphviz
Requires-Dist: matplotlib
Requires-Dist: networkx<4,>=3
Requires-Dist: numpy<3.0,>=1.23
Requires-Dist: pandas
Requires-Dist: plum-dispatch==1.7.3
Requires-Dist: scikit-learn
Requires-Dist: scipy
Requires-Dist: six
Requires-Dist: pydot==1.4.2
Requires-Dist: pyts
Requires-Dist: torch
Requires-Dist: torchdiffeq
Requires-Dist: toml
Requires-Dist: lightning
Requires-Dist: cvxpy
Requires-Dist: cvxpylayers
Requires-Dist: casadi
Requires-Dist: torchsde
Provides-Extra: tests
Requires-Dist: pytest; extra == "tests"
Requires-Dist: hypothesis; extra == "tests"
Provides-Extra: examples
Requires-Dist: imageio; extra == "examples"
Provides-Extra: docs
Requires-Dist: sphinx; extra == "docs"
Requires-Dist: sphinx-rtd-theme; extra == "docs"
Provides-Extra: tracking
Requires-Dist: mlflow<3,>=2.12; extra == "tracking"
Requires-Dist: wandb; extra == "tracking"
Dynamic: license-file
